server.py
tes_mcp-0.1.0.dist-info/METADATA
tes_mcp-0.1.0.dist-info/WHEEL
tes_mcp-0.1.0.dist-info/top_level.txt
tes_mcp-0.1.0.dist-info/RECORD
